fa_mac/__init__.py
fa_mac/__version__.py
fa_mac/shader.py
fa_mac/texture.py
fa_mac/examples/__init__.py
fa_mac/examples/app.py
fa_mac/examples/glfwBackend.py
fieldanimation/__init__.py
fieldanimation/__version__.py
fieldanimation/shader.py
fieldanimation/texture.py
fieldanimation/examples/__init__.py
fieldanimation/examples/app.py
fieldanimation/examples/glfwBackend.py
fieldanimation/glsl/draw.frag
fieldanimation/glsl/draw.vert
fieldanimation/glsl/field.frag
fieldanimation/glsl/field.vert
fieldanimation/glsl/image.frag
fieldanimation/glsl/quad.vert
fieldanimation/glsl/screen.frag
fieldanimation/glsl/update.comp
fieldanimation/glsl/update.frag
fieldanimation-0.1.3a0.dist-info/METADATA
fieldanimation-0.1.3a0.dist-info/WHEEL
fieldanimation-0.1.3a0.dist-info/top_level.txt
fieldanimation-0.1.3a0.dist-info/RECORD
