Metadata-Version: 2.1
Name: fieldanimation
Version: 0.1.3a0
Summary: FieldAnimation: animate 2D vector fields
Home-page: https://bitbucket.org/bvidmar/fieldanimation
Author: Nicola Creati, Roberto Vidmar
Author-email: ncreati@inogs.it
License: MIT
Download-URL: https://bitbucket.org/bvidmar/fieldanimation
Keywords: fieldanimation,OpenGL,Widget,Vector field
Platform: POSIX
Classifier: Development Status :: 4 - Beta
Classifier: Intended Audience :: Developers
Classifier: Intended Audience :: Science/Research
Classifier: License :: OSI Approved :: MIT License
Classifier: Operating System :: POSIX
Classifier: Programming Language :: Python
Classifier: Topic :: Scientific/Engineering :: Visualization
Classifier: Topic :: Software Development :: Libraries :: Python Modules
Requires-Dist: PyOpenGL (>=3.1.0)
Requires-Dist: numpy (>=1.14.3)
Requires-Dist: pip (>=9.0.1)
Requires-Dist: setuptools (>=39.0.1)
